setup.py
bintraypy/__init__.py
bintraypy/bintray.py
bintraypy.egg-info/PKG-INFO
bintraypy.egg-info/SOURCES.txt
bintraypy.egg-info/dependency_links.txt
bintraypy.egg-info/requires.txt
bintraypy.egg-info/top_level.txt