Metadata-Version: 1.0
Name: bintraypy
Version: 0.1.1
Summary: Wrapper for (parts of) the Bintray API
Home-page: http://github.com/Gohla/bintraypy
Author: Gabriel Konat
Author-email: g.d.p.konat@tudelft.nl
License: Apache 2.0
Platform: UNKNOWN
